{"product_id": "214763", "detail_url": "https://www.fonq.nl/product/kave-home-pol-vloerkleed-230-x-160-cm/214763/", "title": "Kave Home Pol Vloerkleed 230 x 160 cm", "price": "198,-", "category": "rugs", "competitor": "fonq", "Breedte": "160 cm", "Lengte": "230 cm", "Productnummer": "203950", "EAN Code": "8433840420073", "Bestelcode": "AA1109J15", "Dessin Vloerkleden": "Vintage", "Garantie": "2 jaar", "Kleur": "Grijs, Zwart", "Materiaal": "Katoen", "Productserie": "Pol", "Type vloerkleed": "Laagpolig", "Vorm": "Rechthoekig"}