{"product_id": "239556", "detail_url": "https://www.fonq.nl/product/bloomingville-arte-deco-vloerkleed-120-x-60-cm/239556/", "title": "Bloomingville Arte Deco Vloerkleed 120 x 60 cm", "price": "41,-", "category": "rugs", "competitor": "fonq", "Breedte": "60 cm", "Lengte": "120 cm", "Productnummer": "228591", "EAN Code": "5711173184019", "Bestelcode": "32700134", "Dessin Vloerkleden": "Grafisch", "Droogvoorschriften": "Niet geschikt voor droger", "Garantie": "2 jaar", "Geschikt voor binnen / buiten": "Binnen", "Kleur": "Beige, Roze", "Materiaal": "Katoen", "Materiaal type": "100% katoen", "Type vloerkleed": "Laagpolig", "Vorm": "Rechthoekig", "Wasvoorschriften": "Niet geschikt voor wasbehandeling"}