{"product_id": "198954", "detail_url": "https://www.fonq.nl/product/kave-home-lars-stoel/198954/", "title": "Kave Home Lars Stoel", "price": "84,-\n\n\n99,-", "category": "dining_chairs", "competitor": "fonq", "Breedte": "47 cm", "Hoogte": "86 cm", "Materiaal onderstel": "Hout", "Materiaal zitting": "Textiel", "Zithoogte": "47 cm", "Diepte": "50 cm", "Zitdiepte": "42 cm", "Productnummer": "187930", "EAN Code": "8433840409993", "Armleuning": "Nee", "Bestelcode": "C632JQ27", "Garantie": "2 jaar", "In hoogte verstelbaar": "Nee", "Kleur": "Blauw", "Kleur poten": "Beige", "Kleur zitting": "Blauw", "Kleurtint": "Light blue", "Materiaal": "Hout, Textiel", "Materiaal type": "Beukenhout", "Maximale draagkracht": "120 kg", "Productserie": "Lars", "Stapelbaar": "Nee", "Wielen": "Nee"}