{"product_id": "284566", "detail_url": "https://www.fonq.nl/product/kare-design-set-2-stoelen-stay-zithoogte-48-cm-velvet-stof-blauw/284566/", "title": "Kare Design Set 2 Stoelen Stay - Zithoogte 48 Cm - Velvet Stof Blauw", "price": "598,-", "category": "dining_chairs", "competitor": "fonq", "Breedte": "56 cm", "Hoogte": "95 cm", "Materiaal onderstel": "Hout", "Materiaal zitting": "Polyester", "Zithoogte": "48 cm", "Diepte": "71 cm", "Maat": "L X B56 X H95 X D71", "Productnummer": "2_016169", "EAN Code": "4025621825814", "Armleuning": "Nee", "Kleur": "Blauw", "Kleurtint": "Blauw", "Materiaal": "Polyester", "Stapelbaar": "Nee"}