{"product_id": "78303", "detail_url": "https://www.fonq.nl/product/resol-dd-netkat-stoel/78303/", "title": "Resol Dd Netkat Stoel", "price": "59,95\n\n\n84,95", "category": "dining_chairs", "competitor": "fonq", "Breedte": "50,5 cm", "Hoogte": "79 cm", "Materiaal onderstel": "Kunststof", "Materiaal zitting": "Kunststof", "Zithoogte": "45 cm", "Diepte": "55,5 cm", "Productnummer": "79515", "EAN Code": "8411344009949", "Afmetingen zitvlak": "L 55,5 x B 50,5 x H 79 cm", "Armleuning": "Nee", "Bestelcode": "00994", "Garantie": "2 jaar", "Gewicht in kg": "3,6 kg", "Kleur": "Groen", "Kleurtint": "Olijf groen", "Ruimte": "Eetkamer", "Stapelbaar": "Ja", "Type tuinstoel": "Bistrostoel"}