{"product_id": "147798", "detail_url": "https://www.fonq.nl/product/foscarini-tress-grande-led-vloerlamp/147798/", "title": "Foscarini Tress Grande LED Vloerlamp", "price": "2.130,85", "category": "floor_lights", "competitor": "fonq", "Fitting": "Ingebouwd (LED)", "Hoogte": "195 cm", "Lichtbron meegeleverd": "Nee", "Materiaal": "Aluminium, Kunststof, Metaal", "Diameter": "20 cm", "Productnummer": "155347", "EAN Code": "", "Aantal lichtbronnen": "1", "Bestelcode": "182003L 10", "Dimmer": "Ingebouwde dimmer", "Elektrische vereisten": "220 - 240 Volt", "Garantie": "2 jaar", "Gewicht in kg": "8,5 kg", "Kleur": "Wit", "Lichtbron": "LED", "Productserie": "Tres", "Ruimte": "Kantoor, Slaapkamer, Woonkamer", "Type lamp": "Vloerlamp", "Type/uitvoering": "LED", "Vermogen (in Watt)": "56", "Voltage": "220-240 Volt"}