{"product_id": "295688", "detail_url": "https://www.fonq.nl/product/light-living-lampvoet-bellini-hout-boerengrijs-m/295688/", "title": "Light & Living Lampvoet BELLINI - hout boerengrijs - M", "price": "91,95", "category": "floor_lights", "competitor": "fonq", "Breedte": "19 cm", "Fitting": "E27", "Hoogte": "78 cm", "Lichtbron meegeleverd": "Nee", "Materiaal": "Hout", "Diameter": "19 cm", "Diepte": "19 cm", "Lengte": "19 cm", "Maat": "19 x 19 cm", "Productnummer": "2_025308", "EAN Code": "8717807135485", "Dimmer": "Geschikt voor dimmer", "Kleur": "Grijs", "Kleurtint": "Grijs", "Lichtbron": "Exclusief", "Vermogen (in Watt)": "40"}