{"product_id": "15843", "detail_url": "https://www.fonq.nl/product/giso-hanglamp-fililite/15843/", "title": "Giso Hanglamp Fililite", "price": "Vanaf\n\n\n48,95", "category": "pendant_lights", "competitor": "fonq", "Breedte": "30 cm", "Fitting": "E27", "Lichtbron meegeleverd": "Nee", "Materiaal": "Glas, Nikkel", "Diameter": "30 cm", "Productnummer": "27465", "EAN Code": "", "Aantal lichtbronnen": "1", "Bestelcode": "'HO-2550/10 Mni", "Elektrische vereisten": "220 - 240 Volt", "Garantie": "2 jaar", "Kleur": "Beige", "Lichtbron": "Halogeen, LED", "Materiaal type": "Mat nikkel", "Ruimte": "Slaapkamer, Woonkamer", "Type/uitvoering": "Hanglamp", "Vermogen (in Watt)": "40"}