{"product_id": "261768", "detail_url": "https://www.fonq.nl/product/beliani-segre-hanglamp-wit-kunststof/261768/", "title": "Beliani Segre Hanglamp Wit Kunststof", "price": "83,-", "category": "pendant_lights", "competitor": "fonq", "Fitting": "E27", "Hoogte": "41 cm", "Lichtbron meegeleverd": "Nee", "Materiaal": "Textiel", "Diameter": "60 cm", "Snoerlengte in meters": "1,25", "Productnummer": "2_000977", "EAN Code": "7081457159605", "Kleur": "Wit", "Kleurtint": "Wit", "Lichtbron": "Exclusief", "Vermogen (in Watt)": "60"}