{"product_id": "126656", "detail_url": "https://www.fonq.nl/product/eth-industry-hanglamp-45-cm/126656/", "title": "ETH Industry Hanglamp \u00d8 45 cm", "price": "67,99\n\n\n99,-", "category": "pendant_lights", "competitor": "fonq", "Fitting": "E27", "Hoogte": "20 cm", "Materiaal": "Aluminium", "Diameter": "45 cm", "Productnummer": "134012", "EAN Code": "8718226348388", "Aantal lichtbronnen": "1", "Bestelcode": "05-HL4366-31", "Dimmer": "Geschikt voor dimmer", "Elektrische vereisten": "220 - 240 Volt", "Garantie": "2 jaar", "Kleur": "Wit", "Lichtbron": "Halogeen, LED", "Ruimte": "Eetkamer, Kantoor, Slaapkamer, Woonkamer", "Vermogen (in Watt)": "60"}