{"product_id": "151103", "detail_url": "https://www.fonq.nl/product/vtwonen-galaxy-hanglamp-71-cm/151103/", "title": "vtwonen Galaxy Hanglamp \u00d8 71 cm", "price": "207,-", "category": "pendant_lights", "competitor": "fonq", "Breedte": "71 cm", "Fitting": "E27", "Hoogte": "32 cm", "Materiaal": "Aluminium", "Diameter": "71 cm", "Productnummer": "158690", "EAN Code": "6001201070001", "Aantal lichtbronnen": "1", "Bestelcode": "60.0120.107", "Dimmer": "Geschikt voor dimmer", "Garantie": "2 jaar", "Kleur": "Zilver", "Lichtbron": "Halogeen, LED", "Vermogen (in Watt)": "100"}