{"product_id": "270297", "detail_url": "https://www.fonq.nl/product/light-living-hanglamp-danita-glas-antiek-brons-s/270297/", "title": "Light & Living Hanglamp DANITA - glas antiek brons - S", "price": "52,95", "category": "pendant_lights", "competitor": "fonq", "Breedte": "17 cm", "Fitting": "E27", "Hoogte": "22 cm", "Lichtbron meegeleverd": "Nee", "Materiaal": "Glas", "Diameter": "17 cm", "Diepte": "17 cm", "Lengte": "17 cm", "Maat": "17 x 17 cm", "Snoerlengte in meters": "120", "Productnummer": "2_005648", "EAN Code": "8717807242817", "Aantal lichtbronnen": "1", "Dimmer": "Geschikt voor dimmer", "Kleur": "Brons", "Kleurtint": "Brons", "Lichtbron": "Exclusief", "Vermogen (in Watt)": "40"}