{"product_id": "296105", "detail_url": "https://www.fonq.nl/product/light-living-hanglamp-eelkje-zwart_bruin-zink/296105/", "title": "Light & Living Hanglamp EELKJE - Zwart/Bruin Zink", "price": "74,95", "category": "pendant_lights", "competitor": "fonq", "Breedte": "31 cm", "Fitting": "E27", "Hoogte": "40 cm", "Lichtbron meegeleverd": "Nee", "Materiaal": "Metaal, Zink", "Diameter": "31 cm", "Diepte": "31 cm", "Lengte": "31 cm", "Maat": "31 x 31 cm", "Snoerlengte in meters": "120", "Productnummer": "2_025725", "EAN Code": "8717807188658", "Dimmer": "Geschikt voor dimmer", "Kleur": "Bruin, Zwart", "Kleurtint": "Zwart,Bruin", "Lichtbron": "Exclusief", "Vermogen (in Watt)": "40"}