{"product_id": "329554", "detail_url": "https://www.fonq.nl/product/steinhauer-roundy-hanglamp-rvs/329554/", "title": "Steinhauer Roundy Hanglamp RVS", "price": "49,95", "category": "pendant_lights", "competitor": "fonq", "Breedte": "18 cm", "Fitting": "Ingebouwd (LED)", "Hoogte": "125 cm", "Lichtbron meegeleverd": "Ja", "Materiaal": "Metaal", "Lengte": "125 cm", "Snoerlengte in meters": "1", "Productnummer": "2_057659", "EAN Code": "8712746103090", "Aantal lichtbronnen": "1", "Dimmer": "Geschikt voor dimmer", "Kleur": "RVS", "Kleurtint": "RVS"}