{"product_id": "262985", "detail_url": "https://www.fonq.nl/product/woood-muck-eetkamerstoel/262985/", "title": "Woood Muck Eetkamerstoel", "price": "119,-", "category": "dining_chairs", "competitor": "fonq", "Breedte": "51,5 cm", "Hoogte": "78 cm", "Materiaal onderstel": "Metaal", "Materiaal zitting": "Metaal", "Zithoogte": "45 cm", "Diepte": "54 cm", "Zitdiepte": "40 cm", "Productnummer": "241295", "EAN Code": "8714713074495", "Bestelcode": "373574-Z", "Garantie": "2 jaar", "Kleurtint": "Zwart", "Productserie": "Muck"}