{"product_id": "245211", "detail_url": "https://www.fonq.nl/product/hart-ruyt-jut-wandlamp_nachtkastje/245211/", "title": "Hart & Ruyt Jut Wandlamp/Nachtkastje", "price": "186,15\n\n\n219,-", "category": "wall_lights", "competitor": "fonq", "Breedte": "35 cm", "Fitting": "E27", "Hoogte": "13 cm", "Materiaal": "Glas, Hout", "Wandlamp aansluiting": "Met stekker", "Diameter": "37 cm", "Diepte": "12 cm", "Snoerlengte in meters": "2", "Productnummer": "234342", "EAN Code": "3871918532962", "Aantal lichtbronnen": "1", "Bestelcode": "Jut", "Dimmer": "Geschikt voor dimmer", "Garantie": "2 jaar", "Kleur": "Bruin", "Lades": "Nee", "Lichtbron": "LED", "Lichtbron meegeleverd": "Nee", "Lichtrichting": "Rondom", "Materiaal type": "Walnoothout", "Productserie": "Jut en Jul", "Vermogen (in Watt)": "10"}