{"product_id": "266793", "detail_url": "https://www.fonq.nl/product/trio-dylan-wandlamp/266793/", "title": "TRIO Dylan Wandlamp", "price": "69,95\n\n\n77,70", "category": "wall_lights", "competitor": "fonq", "Breedte": "13 cm", "Fitting": "SMD LED", "Hoogte": "34,5 cm", "Materiaal": "Metaal", "Wandlamp aansluiting": "Op het lichtnet", "Diepte": "8,8 cm", "Maat": "H 34,5 x B 13 x D 8,8 cm", "Productnummer": "243761", "EAN Code": "4017807395198", "Aantal lichtbronnen": "2", "Bestelcode": "283370206", "Dimbaar": "Nee", "Dimmer": "Niet geschikt voor dimmer", "Energielabel": "A+", "Garantie": "2 jaar", "Kleur": "Zilver", "Kleurtint": "Chroom", "Lichtbron": "LED", "Lichtbron meegeleverd": "Ja", "Lichtkleur": "Warm wit (2700K-3000K)", "Lichtrichting": "Rondom", "Productserie": "Dylan", "Vermogen (in Watt)": "4"}