{"product_id": "115146", "detail_url": "https://www.fonq.nl/product/artemide-teti-wandlamp_plafondlamp/115146/", "title": "Artemide Teti Wandlamp/Plafondlamp", "price": "40,60\n\n\n48,-", "category": "wall_lights", "competitor": "fonq", "Breedte": "14 cm", "Fitting": "E27", "Hoogte": "14 cm", "Lichtbron meegeleverd": "Nee", "Materiaal": "Kunststof", "Diameter": "14 cm", "Productnummer": "122557", "EAN Code": "8052993019844", "Aantal lichtbronnen": "1", "Bestelcode": "A048120", "Elektrische vereisten": "220 - 240 Volt", "Garantie": "2 jaar", "Geschikt voor badkamer": "Nee", "IP-waarde": "20", "Kleur": "Wit", "Kleurtint": "Wit", "Lichtbron": "LED", "Lichtrichting": "Naar beneden, Rondom", "Ruimte": "Kantoor, Slaapkamer, Woonkamer", "Soort": "Wandlamp,Plafondlamp", "Type lamp": "E27 max 28W", "Vermogen (in Watt)": "28", "Voltage": "220-240 Volt", "Vorm": "Rond", "Wandlamp aansluiting": "Op het lichtnet"}