{"product_id": "149498", "detail_url": "https://www.fonq.nl/product/tenzo-gina-stoel/149498/", "title": "Tenzo Gina Stoel", "price": "108,-", "category": "dining_chairs", "competitor": "fonq", "Breedte": "51 cm", "Hoogte": "82 cm", "Materiaal onderstel": "Metaal", "Materiaal zitting": "Kunststof", "Zithoogte": "45 cm", "Diepte": "49 cm", "Zitdiepte": "42 cm", "Productnummer": "1456", "EAN Code": "", "Armleuning": "Nee", "Garantie": "2 jaar", "Kleur": "Grijs", "Kleurtint": "Warm Grijs", "Materiaal": "Kunststof, Metaal, Textiel", "Materiaal type": "Polypropyleen en gepoedercoad metaal", "Maximale draagkracht": "125 kg", "Onderstel": "Porgy Wit", "Stapelbaar": "Nee"}