{"product_id": "51544", "detail_url": "https://www.fonq.nl/product/magis-chair-first-stoel/51544/", "title": "Magis Chair First Stoel", "price": "80,95", "category": "dining_chairs", "competitor": "fonq", "Breedte": "50 cm", "Hoogte": "77,5 cm", "Materiaal onderstel": "Kunststof", "Materiaal zitting": "Kunststof", "Zithoogte": "46,5 cm", "Diepte": "52 cm", "Productnummer": "75364", "EAN Code": "", "Armleuning": "Nee", "Bestelcode": "SD800/1153C", "Garantie": "2 jaar", "Kleur": "Paars", "Materiaal type": "Polypropyleen en Glasfiber", "Productserie": "First", "Ruimte": "Eetkamer", "Stapelbaar": "Ja", "Wielen": "Nee"}