{"product_id": "333672", "detail_url": "https://www.fonq.nl/product/light-living-lampvoet-spring-ruw-antiek-brons/333672/", "title": "Light & Living Lampvoet SPRING - ruw antiek brons", "price": "105,95", "category": "floor_lights", "competitor": "fonq", "Breedte": "20 cm", "Fitting": "E27", "Hoogte": "61 cm", "Lichtbron meegeleverd": "Nee", "Materiaal": "Metaal", "Diameter": "13 cm", "Diepte": "13 cm", "Lengte": "20 cm", "Maat": "20 x 13 cm", "Productnummer": "2_060589", "EAN Code": "8717807197513", "Dimmer": "Geschikt voor dimmer", "Kleur": "Brons", "Kleurtint": "Brons", "Lichtbron": "Exclusief", "Vermogen (in Watt)": "40"}