{"product_id": "147665", "detail_url": "https://www.fonq.nl/product/umage-eos-hanglamp-m-45-cm/147665/", "title": "Umage Eos Hanglamp M \u00d8 45 cm", "price": "128,95", "category": "pendant_lights", "competitor": "fonq", "Breedte": "45 cm", "Fitting": "E27", "Hoogte": "30 cm", "Materiaal": "Papier, Textiel", "Diameter": "45 cm", "Snoerlengte in meters": "2,1", "Productnummer": "1396", "EAN Code": "", "Aantal lichtbronnen": "1", "Dimmer": "Geschikt voor dimmer", "Garantie": "2 jaar", "Kleur": "Cr\u00e8me", "Lichtbron": "Halogeen, LED", "Materiaal type": "Ganzenveren", "Meegeleverd in de doos": "Zwart koord en fitting", "Ruimte": "Kantoor, Slaapkamer, Woonkamer", "Vermogen (in Watt)": "60"}