{"product_id": "230907", "detail_url": "https://www.fonq.nl/product/alessi-girotondo-tafellamp/230907/", "title": "Alessi Girotondo Tafellamp", "price": "68,-", "category": "table_lights", "competitor": "fonq", "Breedte": "14 cm", "Hoogte": "20 cm", "Materiaal": "Kunststof", "Diepte": "4,5 cm", "Productnummer": "219907", "EAN Code": "8003299415991", "Bestelcode": "AKK86 P", "Garantie": "2 jaar", "Geschenkverpakking": "Ja", "Kleur": "Roze", "Lichtbron": "Halogeen, LED", "Productserie": "Alessi Girotondo", "Snoerloos": "Ja", "Vaatwasserbestendig": "Nee"}